linak_ctrl/__init__.py
linak_ctrl-1.0.4.dist-info/AUTHORS
linak_ctrl-1.0.4.dist-info/LICENSE
linak_ctrl-1.0.4.dist-info/METADATA
linak_ctrl-1.0.4.dist-info/WHEEL
linak_ctrl-1.0.4.dist-info/entry_points.txt
linak_ctrl-1.0.4.dist-info/pbr.json
linak_ctrl-1.0.4.dist-info/top_level.txt
linak_ctrl-1.0.4.dist-info/RECORD
