Metadata-Version: 2.1
Name: linak-ctrl
Version: 1.0.4
Summary: Control Linak powered desks using USB2LIN06 cable.
Home-page: https://github.com/gryf/linak-ctrl
Author: Roman Dobosz
Author-email: gryf73@gmail.com
License: BSD
Platform: UNKNOWN
Classifier: Development Status :: 5 - Production/Stable
Classifier: Environment :: Console
Classifier: Intended Audience :: End Users/Desktop
Classifier: License :: OSI Approved :: BSD License
Classifier: Operating System :: POSIX :: Linux
Classifier: Programming Language :: Python
Classifier: Programming Language :: Python :: 3
Classifier: Programming Language :: Python :: 3.7
Classifier: Programming Language :: Python :: 3.8
Classifier: Programming Language :: Python :: 3.9
Classifier: Topic :: System :: Networking
License-File: LICENSE
License-File: AUTHORS
Requires-Dist: pbr
Requires-Dist: pyusb (>=1.1.1)
